[
  {
    "inputs": [],
    "stateMutability": "nonpayable",
    "type": "constructor"
  },
  {
    "inputs": [
      {
        "internalType": "address",
        "name": "addr",
        "type": "address"
      }
    ],
    "name": "AlreadyRegistered",
    "type": "error"
  },
  {
    "inputs": [],
    "name": "InvalidCommit",
    "type": "error"
  },
  {
    "inputs": [],
    "name": "NotAuthorized",
    "type": "error"
  },
  {
    "inputs": [
      {
        "internalType": "address",
        "name": "addr",
        "type": "address"
      }
    ],
    "name": "NotRegistered",
    "type": "error"
  },
  {
    "inputs": [
      {
        "internalType": "uint256",
        "name": "poolSize",
        "type": "uint256"
      },
      {
        "internalType": "uint256",
        "name": "required",
        "type": "uint256"
      }
    ],
    "name": "PoolTooSmall",
    "type": "error"
  },
  {
    "inputs": [
      {
        "internalType": "bytes32",
        "name": "requestId",
        "type": "bytes32"
      }
    ],
    "name": "RequestAlreadyFulfilled",
    "type": "error"
  },
  {
    "inputs": [
      {
        "internalType": "bytes32",
        "name": "requestId",
        "type": "bytes32"
      }
    ],
    "name": "RequestNotFound",
    "type": "error"
  },
  {
    "inputs": [
      {
        "internalType": "uint256",
        "name": "currentBlock",
        "type": "uint256"
      },
      {
        "internalType": "uint256",
        "name": "revealBlock",
        "type": "uint256"
      }
    ],
    "name": "RevealTooEarly",
    "type": "error"
  },
  {
    "inputs": [],
    "name": "RevealTooLate",
    "type": "error"
  },
  {
    "inputs": [],
    "name": "SecretMismatch",
    "type": "error"
  },
  {
    "inputs": [],
    "name": "ZeroAddress",
    "type": "error"
  },
  {
    "anonymous": false,
    "inputs": [
      {
        "indexed": true,
        "internalType": "address",
        "name": "addr",
        "type": "address"
      }
    ],
    "name": "AddressDeregistered",
    "type": "event"
  },
  {
    "anonymous": false,
    "inputs": [
      {
        "indexed": true,
        "internalType": "address",
        "name": "addr",
        "type": "address"
      }
    ],
    "name": "AddressRegistered",
    "type": "event"
  },
  {
    "anonymous": false,
    "inputs": [
      {
        "indexed": true,
        "internalType": "address",
        "name": "requester",
        "type": "address"
      }
    ],
    "name": "AuthorizedRequesterAdded",
    "type": "event"
  },
  {
    "anonymous": false,
    "inputs": [
      {
        "indexed": true,
        "internalType": "address",
        "name": "requester",
        "type": "address"
      }
    ],
    "name": "AuthorizedRequesterRemoved",
    "type": "event"
  },
  {
    "anonymous": false,
    "inputs": [
      {
        "indexed": true,
        "internalType": "bytes32",
        "name": "requestId",
        "type": "bytes32"
      },
      {
        "indexed": false,
        "internalType": "address[]",
        "name": "selected",
        "type": "address[]"
      },
      {
        "indexed": false,
        "internalType": "bytes32",
        "name": "randomness",
        "type": "bytes32"
      }
    ],
    "name": "RandomnessFulfilled",
    "type": "event"
  },
  {
    "anonymous": false,
    "inputs": [
      {
        "indexed": true,
        "internalType": "bytes32",
        "name": "requestId",
        "type": "bytes32"
      },
      {
        "indexed": true,
        "internalType": "address",
        "name": "requester",
        "type": "address"
      },
      {
        "indexed": false,
        "internalType": "uint256",
        "name": "count",
        "type": "uint256"
      },
      {
        "indexed": false,
        "internalType": "bytes32",
        "name": "purpose",
        "type": "bytes32"
      },
      {
        "indexed": false,
        "internalType": "uint256",
        "name": "commitBlock",
        "type": "uint256"
      }
    ],
    "name": "RandomnessRequested",
    "type": "event"
  },
  {
    "inputs": [],
    "name": "REVEAL_DELAY",
    "outputs": [
      {
        "internalType": "uint256",
        "name": "",
        "type": "uint256"
      }
    ],
    "stateMutability": "view",
    "type": "function"
  },
  {
    "inputs": [],
    "name": "REVEAL_WINDOW",
    "outputs": [
      {
        "internalType": "uint256",
        "name": "",
        "type": "uint256"
      }
    ],
    "stateMutability": "view",
    "type": "function"
  },
  {
    "inputs": [
      {
        "internalType": "address",
        "name": "requester",
        "type": "address"
      }
    ],
    "name": "addAuthorizedRequester",
    "outputs": [],
    "stateMutability": "nonpayable",
    "type": "function"
  },
  {
    "inputs": [
      {
        "internalType": "address",
        "name": "",
        "type": "address"
      }
    ],
    "name": "authorizedRequesters",
    "outputs": [
      {
        "internalType": "bool",
        "name": "",
        "type": "bool"
      }
    ],
    "stateMutability": "view",
    "type": "function"
  },
  {
    "inputs": [
      {
        "internalType": "bytes32",
        "name": "secretHash",
        "type": "bytes32"
      },
      {
        "internalType": "uint256",
        "name": "count",
        "type": "uint256"
      },
      {
        "internalType": "bytes32",
        "name": "purpose",
        "type": "bytes32"
      }
    ],
    "name": "commitRandomness",
    "outputs": [
      {
        "internalType": "bytes32",
        "name": "requestId",
        "type": "bytes32"
      }
    ],
    "stateMutability": "nonpayable",
    "type": "function"
  },
  {
    "inputs": [
      {
        "internalType": "address",
        "name": "addr",
        "type": "address"
      }
    ],
    "name": "deregisterAddress",
    "outputs": [],
    "stateMutability": "nonpayable",
    "type": "function"
  },
  {
    "inputs": [],
    "name": "getPool",
    "outputs": [
      {
        "internalType": "address[]",
        "name": "",
        "type": "address[]"
      }
    ],
    "stateMutability": "view",
    "type": "function"
  },
  {
    "inputs": [],
    "name": "getPoolSize",
    "outputs": [
      {
        "internalType": "uint256",
        "name": "",
        "type": "uint256"
      }
    ],
    "stateMutability": "view",
    "type": "function"
  },
  {
    "inputs": [
      {
        "internalType": "bytes32",
        "name": "requestId",
        "type": "bytes32"
      }
    ],
    "name": "getRequest",
    "outputs": [
      {
        "components": [
          {
            "internalType": "address",
            "name": "requester",
            "type": "address"
          },
          {
            "internalType": "uint256",
            "name": "count",
            "type": "uint256"
          },
          {
            "internalType": "bytes32",
            "name": "purpose",
            "type": "bytes32"
          },
          {
            "internalType": "bytes32",
            "name": "secretHash",
            "type": "bytes32"
          },
          {
            "internalType": "uint256",
            "name": "commitBlock",
            "type": "uint256"
          },
          {
            "internalType": "bool",
            "name": "fulfilled",
            "type": "bool"
          },
          {
            "internalType": "address[]",
            "name": "selected",
            "type": "address[]"
          }
        ],
        "internalType": "struct VRFCoordinator.VRFRequest",
        "name": "",
        "type": "tuple"
      }
    ],
    "stateMutability": "view",
    "type": "function"
  },
  {
    "inputs": [
      {
        "internalType": "bytes32",
        "name": "requestId",
        "type": "bytes32"
      }
    ],
    "name": "getSelection",
    "outputs": [
      {
        "internalType": "address[]",
        "name": "",
        "type": "address[]"
      }
    ],
    "stateMutability": "view",
    "type": "function"
  },
  {
    "inputs": [
      {
        "internalType": "address",
        "name": "",
        "type": "address"
      }
    ],
    "name": "inPool",
    "outputs": [
      {
        "internalType": "bool",
        "name": "",
        "type": "bool"
      }
    ],
    "stateMutability": "view",
    "type": "function"
  },
  {
    "inputs": [
      {
        "internalType": "bytes32",
        "name": "requestId",
        "type": "bytes32"
      }
    ],
    "name": "isFulfilled",
    "outputs": [
      {
        "internalType": "bool",
        "name": "",
        "type": "bool"
      }
    ],
    "stateMutability": "view",
    "type": "function"
  },
  {
    "inputs": [],
    "name": "owner",
    "outputs": [
      {
        "internalType": "address",
        "name": "",
        "type": "address"
      }
    ],
    "stateMutability": "view",
    "type": "function"
  },
  {
    "inputs": [
      {
        "internalType": "uint256",
        "name": "",
        "type": "uint256"
      }
    ],
    "name": "pool",
    "outputs": [
      {
        "internalType": "address",
        "name": "",
        "type": "address"
      }
    ],
    "stateMutability": "view",
    "type": "function"
  },
  {
    "inputs": [
      {
        "internalType": "address",
        "name": "addr",
        "type": "address"
      }
    ],
    "name": "registerAddress",
    "outputs": [],
    "stateMutability": "nonpayable",
    "type": "function"
  },
  {
    "inputs": [
      {
        "internalType": "address",
        "name": "requester",
        "type": "address"
      }
    ],
    "name": "removeAuthorizedRequester",
    "outputs": [],
    "stateMutability": "nonpayable",
    "type": "function"
  },
  {
    "inputs": [
      {
        "internalType": "bytes32",
        "name": "",
        "type": "bytes32"
      }
    ],
    "name": "requests",
    "outputs": [
      {
        "internalType": "address",
        "name": "requester",
        "type": "address"
      },
      {
        "internalType": "uint256",
        "name": "count",
        "type": "uint256"
      },
      {
        "internalType": "bytes32",
        "name": "purpose",
        "type": "bytes32"
      },
      {
        "internalType": "bytes32",
        "name": "secretHash",
        "type": "bytes32"
      },
      {
        "internalType": "uint256",
        "name": "commitBlock",
        "type": "uint256"
      },
      {
        "internalType": "bool",
        "name": "fulfilled",
        "type": "bool"
      }
    ],
    "stateMutability": "view",
    "type": "function"
  },
  {
    "inputs": [
      {
        "internalType": "bytes32",
        "name": "requestId",
        "type": "bytes32"
      },
      {
        "internalType": "bytes32",
        "name": "secret",
        "type": "bytes32"
      }
    ],
    "name": "revealAndSelect",
    "outputs": [
      {
        "internalType": "address[]",
        "name": "selected",
        "type": "address[]"
      }
    ],
    "stateMutability": "nonpayable",
    "type": "function"
  }
]